telcoDuty
