Metadata-Version: 1.0
Name: telcoDuty
Version: 0.1.3
Summary: Telco duty routine helper
Home-page: https://pypi.python.org/simple/telcoDuty
Author: Me
Author-email: alexey.grachev@nordigy.ru
License: PSF
Keywords: hello world example examples
Platform: UNKNOWN
